{"_type":"export","__export_format":4,"__export_date":"2020-04-05T15:02:18.067Z","__export_source":"insomnia.desktop.app:v7.1.1","resources":[{"_id":"req_8c6ce96d2d3c4a8ea34a88668627de67","authentication":{},"body":{},"created":1586098158140,"description":"","headers":[],"isPrivate":false,"metaSortKey":-1586098158140,"method":"GET","modified":1586098164972,"name":"list","parameters":[],"parentId":"fld_ecd7a825df0e41c7898b9fd3b9b6dce5","settingDisableRenderRequestBody":false,"settingEncodeUrl":true,"settingFollowRedirects":"global","settingRebuildPath":true,"settingSendCookies":true,"settingStoreCookies":true,"url":"{{server}}/doctors","_type":"request"},{"_id":"fld_ecd7a825df0e41c7898b9fd3b9b6dce5","created":1586098151029,"description":"","environment":{},"environmentPropertyOrder":null,"metaSortKey":-1586098151029,"modified":1586098151029,"name":"doctor","parentId":"wrk_38943ebf7b4147d2bada9062fcbc7b16","_type":"request_group"},{"_id":"wrk_38943ebf7b4147d2bada9062fcbc7b16","created":1586098055837,"description":"","modified":1586098055837,"name":"HMS","parentId":null,"_type":"workspace"},{"_id":"req_06049d9822804c58a8bc4a729134c851","authentication":{},"body":{"mimeType":"application/json","text":"{\n\t\"code\": \"1111\",\n\t\"externalId\": \"1243445235243\",\n\t\"person\": {\n\t\t\"firstName\": \"John\",\n\t\t\"lastName\": \"Lennon\",\n\t\t\"dateOfBirth\": \"20/12/1990\",\n\t\t\"phoneNumber\": \"1223212333\"\n\t},\n\t\"designation\": \"Senior Doctor\",\n\t\"specialties\": [\n\t\t\"physician\", \"heart\"\n\t]\n}"},"created":1586098181852,"description":"","headers":[{"id":"pair_64be6c534eca4d90bfc3a11c336ac089","name":"Content-Type","value":"application/json"}],"isPrivate":false,"metaSortKey":-1586098146597.5,"method":"POST","modified":1586098866705,"name":"create","parameters":[],"parentId":"fld_ecd7a825df0e41c7898b9fd3b9b6dce5","settingDisableRenderRequestBody":false,"settingEncodeUrl":true,"settingFollowRedirects":"global","settingRebuildPath":true,"settingSendCookies":true,"settingStoreCookies":true,"url":"{{server}}/doctors","_type":"request"},{"_id":"req_89062de96d3f4285a94d3aa07d93744c","authentication":{},"body":{"mimeType":"application/json","text":""},"created":1586098875464,"description":"","headers":[{"id":"pair_64be6c534eca4d90bfc3a11c336ac089","name":"Content-Type","value":"application/json"}],"isPrivate":false,"metaSortKey":-1586098140826.25,"method":"DELETE","modified":1586098888477,"name":"delete","parameters":[],"parentId":"fld_ecd7a825df0e41c7898b9fd3b9b6dce5","settingDisableRenderRequestBody":false,"settingEncodeUrl":true,"settingFollowRedirects":"global","settingRebuildPath":true,"settingSendCookies":true,"settingStoreCookies":true,"url":"{{server}}/doctors/2","_type":"request"},{"_id":"req_698d0143430c4eba9fcd4d5bfa76838e","authentication":{},"body":{},"created":1586098135055,"description":"","headers":[],"isPrivate":false,"metaSortKey":-1586098135055,"method":"GET","modified":1586098142008,"name":"Base","parameters":[],"parentId":"wrk_38943ebf7b4147d2bada9062fcbc7b16","settingDisableRenderRequestBody":false,"settingEncodeUrl":true,"settingFollowRedirects":"global","settingRebuildPath":true,"settingSendCookies":true,"settingStoreCookies":true,"url":"{{server}}/","_type":"request"},{"_id":"env_949a8ee0fc43ae4b7bac02106946f689b1963fb4","color":null,"created":1586098056002,"data":{},"dataPropertyOrder":null,"isPrivate":false,"metaSortKey":1586098056003,"modified":1586098056002,"name":"Base Environment","parentId":"wrk_38943ebf7b4147d2bada9062fcbc7b16","_type":"environment"},{"_id":"jar_949a8ee0fc43ae4b7bac02106946f689b1963fb4","cookies":[],"created":1586098056005,"modified":1586098056005,"name":"Default Jar","parentId":"wrk_38943ebf7b4147d2bada9062fcbc7b16","_type":"cookie_jar"},{"_id":"env_d60df965fd2e48a189279e580d87949b","color":null,"created":1586098074273,"data":{"server":"http://localhost:8080"},"dataPropertyOrder":{"&":["server"]},"isPrivate":false,"metaSortKey":1586098074273,"modified":1586098093709,"name":"local","parentId":"env_949a8ee0fc43ae4b7bac02106946f689b1963fb4","_type":"environment"}]}